<?xml version="1.0" encoding="utf-8"?>
<Patch>	

	<Operation Class="PatchOperationFindMod">
		<mods>
			<li>Vanilla Races Expanded - Waster</li>
		</mods>
		<match Class="PatchOperationSequence">
			<operations>
				<li Class="PatchOperationReplace">
					<xpath>Defs/GeneDef[defName="VRE_Instability_Nominal"]/statFactors</xpath>
					<value>
						<statFactors>
							<LifespanFactor>0.9</LifespanFactor>
							<CancerRate>2</CancerRate>
						</statFactors>
					</value>
				</li>
				<li Class="PatchOperationReplace">
					<xpath>Defs/GeneDef[defName="Instability_Mild"]/statFactors</xpath>
					<value>
						<statFactors>
							<LifespanFactor>0.8</LifespanFactor>
							<CancerRate>4</CancerRate>
							<ImmunityGainSpeed>0.95</ImmunityGainSpeed>
						</statFactors>
					</value>
				</li>
				<li Class="PatchOperationReplace">
					<xpath>Defs/GeneDef[defName="Instability_Major"]/statFactors</xpath>
					<value>
						<statFactors>
							<LifespanFactor>0.6</LifespanFactor>
							<CancerRate>6</CancerRate>
							<ImmunityGainSpeed>0.90</ImmunityGainSpeed>
						</statFactors>
					</value>
				</li>

				<li Class="PatchOperationReplace">
					<xpath>Defs/HediffDef[defName="VRE_PollutionRegeneration"]/stages</xpath>
					<value>
						<stages>
							<li>
								<label>inactive</label>
								<minSeverity>0.01</minSeverity>
							</li>
							<li>
								<label>minor</label>
								<minSeverity>0.02</minSeverity>
								<statOffsets>
									<InjuryHealingFactor>1</InjuryHealingFactor>
								</statOffsets>
							</li>
							<li>
								<label>moderate</label>
								<minSeverity>0.20</minSeverity>
								<statOffsets>
									<InjuryHealingFactor>2</InjuryHealingFactor>
								</statOffsets>
							</li>
							<li>
								<label>extreme</label>
								<minSeverity>0.50</minSeverity>
								<statOffsets>
									<InjuryHealingFactor>3</InjuryHealingFactor>
								</statOffsets>
							</li>
						</stages>
					</value>
				</li>
				<li Class="PatchOperationReplace">
					<xpath>Defs/HediffDef[defName="VRE_PollutionRage"]/stages</xpath>
					<value>
						<stages>
							<li>
								<label>inactive</label>
								<minSeverity>0.01</minSeverity>
							</li>
							<li>
								<label>minor</label>
								<minSeverity>0.02</minSeverity>
								<statOffsets>
									<MeleeDamageFactor>0.1</MeleeDamageFactor>
								</statOffsets>
							</li>
							<li>
								<label>moderate</label>
								<minSeverity>0.20</minSeverity>
								<statOffsets>
									<MeleeDamageFactor>0.2</MeleeDamageFactor>
								</statOffsets>
							</li>
							<li>
								<label>extreme</label>
								<minSeverity>0.50</minSeverity>
								<statOffsets>
									<MeleeDamageFactor>0.3</MeleeDamageFactor>
								</statOffsets>
							</li>
						</stages>
					</value>
				</li>
				<li Class="PatchOperationReplace">
					<xpath>Defs/HediffDef[defName="VRE_PollutionSustenance"]/stages</xpath>
					<value>
						<stages>
							<li>
								<label>inactive</label>
								<minSeverity>0.01</minSeverity>
							</li>
							<li>
								<label>minor</label>
								<minSeverity>0.02</minSeverity>
								<hungerRateFactorOffset>-0.1</hungerRateFactorOffset>
							</li>
							<li>
								<label>moderate</label>
								<minSeverity>0.20</minSeverity>
								<hungerRateFactorOffset>-0.3</hungerRateFactorOffset>
							</li>
							<li>
								<label>extreme</label>
								<minSeverity>0.50</minSeverity>
								<hungerRateFactorOffset>-0.5</hungerRateFactorOffset>
							</li>
						</stages>
					</value>
				</li>
				<li Class="PatchOperationReplace">
					<xpath>Defs/HediffDef[defName="VRE_PollutionCognition"]/stages</xpath>
					<value>
						<stages>
							<li>
								<label>inactive</label>
								<minSeverity>0.01</minSeverity>
							</li>
							<li>
								<label>minor</label>
								<minSeverity>0.02</minSeverity>
								<statOffsets>
									<GlobalLearningFactor>0.1</GlobalLearningFactor>
								</statOffsets>
							</li>
							<li>
								<label>moderate</label>
								<minSeverity>0.20</minSeverity>
								<statOffsets>
									<GlobalLearningFactor>0.3</GlobalLearningFactor>
								</statOffsets>
							</li>
							<li>
								<label>extreme</label>
								<minSeverity>0.50</minSeverity>
								<statOffsets>
									<GlobalLearningFactor>0.5</GlobalLearningFactor>
								</statOffsets>
							</li>
						</stages>
					</value>
				</li>
				<li Class="PatchOperationReplace">
					<xpath>Defs/HediffDef[defName="VRE_PollutionNumbness"]/stages</xpath>
					<value>
						<stages>
							<li>
								<label>inactive</label>
								<minSeverity>0.01</minSeverity>
							</li>
							<li>
								<label>minor</label>
								<minSeverity>0.02</minSeverity>
								<painFactor>0.9</painFactor>
							</li>
							<li>
								<label>moderate</label>
								<minSeverity>0.20</minSeverity>
								<painFactor>0.7</painFactor>
							</li>
							<li>
								<label>extreme</label>
								<minSeverity>0.50</minSeverity>
								<painFactor>0.5</painFactor>
							</li>
						</stages>
					</value>
				</li>
				<li Class="PatchOperationReplace">
					<xpath>Defs/HediffDef[defName="VRE_PollutionProductivity"]/stages</xpath>
					<value>
						<stages>
							<li>
								<label>inactive</label>
								<minSeverity>0.01</minSeverity>
							</li>
							<li>
								<label>minor</label>
								<minSeverity>0.02</minSeverity>	
								<statOffsets>
									<WorkSpeedGlobal>0.1</WorkSpeedGlobal>
								</statOffsets>
							</li>
							<li>
								<label>moderate</label>
								<minSeverity>0.20</minSeverity>
								<statOffsets>
									<WorkSpeedGlobal>0.2</WorkSpeedGlobal>
								</statOffsets>
							</li>
							<li>
								<label>extreme</label>
								<minSeverity>0.50</minSeverity>
								<statOffsets>
									<WorkSpeedGlobal>0.3</WorkSpeedGlobal>
								</statOffsets>
							</li>
						</stages>
					</value>
				</li>
				<li Class="PatchOperationReplace">
					<xpath>Defs/HediffDef[defName="VRE_PollutionPsySensitivity"]/stages</xpath>
					<value>
						<stages>
							<li>
								<label>inactive</label>
								<minSeverity>0.01</minSeverity>
							</li>
							<li>
								<label>minor</label>
								<minSeverity>0.02</minSeverity>
								<statOffsets>
									<PsychicSensitivity>0.2</PsychicSensitivity>
								</statOffsets>
							</li>
							<li>
								<label>moderate</label>
								<minSeverity>0.20</minSeverity>
								<statOffsets>
									<PsychicSensitivity>0.3</PsychicSensitivity>
								</statOffsets>
							</li>
							<li>
								<label>extreme</label>
								<minSeverity>0.50</minSeverity>
								<statOffsets>
									<PsychicSensitivity>0.4</PsychicSensitivity>
								</statOffsets>
							</li>
						</stages>
					</value>
				</li>
				<li Class="PatchOperationReplace">
					<xpath>Defs/HediffDef[defName="VRE_PollutionAccuracy"]/stages</xpath>
					<value>
						<stages>
							<li>
								<label>inactive</label>
								<minSeverity>0.01</minSeverity>
							</li>
							<li>
								<label>minor</label>
								<minSeverity>0.02</minSeverity>
								<statFactors>
									<AccuracyLong>1.1</AccuracyLong>
									<AccuracyMedium>1.1</AccuracyMedium>
								</statFactors>
							</li>
							<li>
								<label>moderate</label>
								<minSeverity>0.20</minSeverity>
								<statFactors>
									<AccuracyLong>1.2</AccuracyLong>
									<AccuracyMedium>1.2</AccuracyMedium>
								</statFactors>
							</li>
							<li>
								<label>extreme</label>
								<minSeverity>0.50</minSeverity>
								<statFactors>
									<AccuracyLong>1.3</AccuracyLong>
									<AccuracyMedium>1.3</AccuracyMedium>
								</statFactors>
							</li>
						</stages>
					</value>
				</li>
			</operations>
		</match>
	</Operation>

</Patch>
